fasta_checksum_utils/__init__.py
fasta_checksum_utils/_contig.py
fasta_checksum_utils/_file.py
fasta_checksum_utils/algorithms.py
fasta_checksum_utils/entry.py
fasta_checksum_utils/fasta.py
fasta_checksum_utils-0.5.0.dist-info/METADATA
fasta_checksum_utils-0.5.0.dist-info/WHEEL
fasta_checksum_utils-0.5.0.dist-info/entry_points.txt
fasta_checksum_utils-0.5.0.dist-info/licenses/LICENSE
fasta_checksum_utils-0.5.0.dist-info/RECORD
