Metadata-Version: 2.4
Name: fasta-checksum-utils
Version: 0.5.0
Summary: Library and command-line utility for checksumming FASTA files and individual contigs.
License: LGPL-3.0
License-File: LICENSE
Author: David Lougheed
Author-email: david.lougheed@gmail.com
Requires-Python: >=3.10.0,<3.14
Classifier: License :: OSI Approved :: GNU Lesser General Public License v3 (LGPLv3)
Classifier: Programming Language :: Python :: 3
Classifier: Programming Language :: Python :: 3.10
Classifier: Programming Language :: Python :: 3.11
Classifier: Programming Language :: Python :: 3.12
Classifier: Programming Language :: Python :: 3.13
Requires-Dist: aiofiles (>=23.2.1,<26)
Requires-Dist: aiohttp (>=3.9.3,<4.0.0)
Requires-Dist: pysam (>=0.22.0,<0.24)
